simplecube/__init__.py
simplecube/simplecube_core.py
simplecube-0.9.dist-info/licenses/LICENSE
simplecube-0.9.dist-info/METADATA
simplecube-0.9.dist-info/WHEEL
simplecube-0.9.dist-info/top_level.txt
simplecube-0.9.dist-info/RECORD
