Metadata-Version: 2.4
Name: simplecube
Version: 0.9
Summary: Simple python package for creating satellite image data cubes based on Brazil Data Cube
Home-page: https://github.com/GSansigolo/simplecube
Author: Gabriel Sansigolo
Author-email: gabrielsansigolo@gmail.com
License-File: LICENSE
Requires-Dist: xarray==2024.3.0
Requires-Dist: tqdm==4.66.4
Requires-Dist: numpy
Requires-Dist: urllib3==2.2.2
Requires-Dist: requests==2.32.3
Requires-Dist: pandas==2.2.2
Requires-Dist: scipy==1.13.1
Requires-Dist: datetime==5.5
Requires-Dist: rasterio==1.3.11
Requires-Dist: rioxarray
Requires-Dist: fsspec==2025.9.0
Requires-Dist: aiohttp==3.12.15
Requires-Dist: h5netcdf==1.6.4
Requires-Dist: cfgrib==0.9.15.0
Requires-Dist: pystac_client
Requires-Dist: shapely
Dynamic: author
Dynamic: author-email
Dynamic: description
Dynamic: home-page
Dynamic: license-file
Dynamic: requires-dist
Dynamic: summary
